{
  "name": "Ida Warner",
  "age": 33,
  "address": {
    "street": "Idzi Grove",
    "city": "Wokwiwok",
    "state": "LA",
    "zip": "99043"
  },
  "contact": {
    "phone": "(543) 498-5430",
    "servicePhone": "800351851"
  },
  "birthday": "1991-02-16T04:41:47.205Z",
  "ip": "114.248.51.63",
  "foo": "bar",
  "profile": {
    "about": "Venani vosopo pah udoce recraji pup pijuasu disnul wuawedu toezew lew buf hupgoci vifca nerpolam cabrabe. Memaflar pav onna henekvob jagcot zewe hiv be he bop ed vef kodi. Mo pocamtik umajel goruhtit ufrezwi isdecanu igawmo ga danze mebgen ho nasmovak tuk or.",
    "bio": "Witi osifa wa higonan cuek ugge ru tegur uw ihusu daremi pacuvun cuk dafgupur. Cermej reuhe iguhi ow wivpeh zewret kuttur jeeba tikecze ruwu vozfufcav dorhu somip ilunurfen. Nicob sitgob curocdi ajmiswo semci momogku uru dupsofa we epufun hu bo. Olu uzuf sebav koceumu ni sopudguv em sifa usipesen bazcocvi ofuho tehijne dakmusig wulbo monid wikohnen jilmi. Uppawov caram ditpirwur momzucor ranegdu jildascek fuhjah tokda fuvulmop puljerlik lu ahture jup vumtihkik mar. Cah mogodizum nizlezvi zej cikrapi hecazug ko wevnanna romuwot ji wetemi edu simicu tofo uve sub zori. Jeceku te amcuver zocla rahnak bamid giiljon ipi buomfuv vid momavsot vatvaj copami nopisne mehel aruzun."
  },
  "apiKey": "4c077ca8defa28fbf4a27fad9141fc94785cb102d9836f5e6a93267d64ead475",
  "currency": {
    "code": "MWK",
    "name": "Malawi Kwacha"
  }
}